meval/__init__.py
meval-2.5.dist-info/LICENSE
meval-2.5.dist-info/METADATA
meval-2.5.dist-info/WHEEL
meval-2.5.dist-info/top_level.txt
meval-2.5.dist-info/RECORD
