Metadata-Version: 2.1
Name: meval
Version: 2.5
Summary: Performs async evaluations of strings
Home-page: https://github.com/penn5/meval
Author: Hackintosh 5
Author-email: hackintoshfive@gmail.com
License: UNKNOWN
Platform: UNKNOWN
Classifier: Programming Language :: Python :: 3
Classifier: License :: OSI Approved :: MIT License
Classifier: Operating System :: OS Independent
Requires-Python: >=3.5
